ipm/__init__.py
ipm/__main__.py
ipm/__version__.py
ipm/common.py
ipm/manage.py
ipm/version_check.py
cf_ipm-1.2.5.dist-info/LICENSE
cf_ipm-1.2.5.dist-info/METADATA
cf_ipm-1.2.5.dist-info/WHEEL
cf_ipm-1.2.5.dist-info/entry_points.txt
cf_ipm-1.2.5.dist-info/RECORD
