Metadata-Version: 2.1
Name: cf-ipm
Version: 1.2.5
Summary: Package manager for Open Source ASIC IPs
Home-page: https://chipfoundry.io
License: Apache-2.0
Author: ChipFoundry
Author-email: marwan.abbas@chipfoundry.io
Requires-Python: >=3.8.0
Classifier: License :: OSI Approved :: Apache Software License
Classifier: Programming Language :: Python :: 3
Classifier: Programming Language :: Python :: 3.8
Classifier: Programming Language :: Python :: 3.9
Classifier: Programming Language :: Python :: 3.10
Classifier: Programming Language :: Python :: 3.11
Classifier: Programming Language :: Python :: 3.12
Classifier: Programming Language :: Python :: 3.13
Requires-Dist: beautifulsoup4 (>=4.12.0,<5)
Requires-Dist: click (>=8.0.0,<9)
Requires-Dist: click-default-group
Requires-Dist: httpx (>0.22.0,<0.28.0)
Requires-Dist: pyyaml (>=5,<7)
Requires-Dist: requests (>=2.31.0,<3)
Requires-Dist: rich (>=12,<14)
Project-URL: Repository, https://github.com/chipfoundry/ipm
